flix/__init__.py
flix/__main__.py
flix/cli/__init__.py
flix/cli/interactive_client.py
flix/cli/main.py
flix/extension/__init__.py
flix/extension/client.py
flix/extension/extension_api/__init__.py
flix/extension/extension_api/api/__init__.py
flix/extension/extension_api/api/api_registration/__init__.py
flix/extension/extension_api/api/api_registration/registration_controller_get_all.py
flix/extension/extension_api/api/api_registration/registration_controller_register_client.py
flix/extension/extension_api/api/api_registration/registration_controller_unregister_client.py
flix/extension/extension_api/api/health_check/__init__.py
flix/extension/extension_api/api/health_check/health_check_controller_health_check.py
flix/extension/extension_api/api/media_object_download/__init__.py
flix/extension/extension_api/api/media_object_download/download_controller_download_media_object.py
flix/extension/extension_api/api/panel_management/__init__.py
flix/extension/extension_api/api/panel_management/panel_controller_annotate.py
flix/extension/extension_api/api/panel_management/panel_controller_create.py
flix/extension/extension_api/api/panel_management/panel_controller_update.py
flix/extension/extension_api/api/project_details/__init__.py
flix/extension/extension_api/api/project_details/project_controller_get.py
flix/extension/extension_api/api/status/__init__.py
flix/extension/extension_api/api/status/status_controller_get.py
flix/extension/extension_api/client.py
flix/extension/extension_api/errors.py
flix/extension/extension_api/models/__init__.py
flix/extension/extension_api/models/action_event.py
flix/extension/extension_api/models/action_state.py
flix/extension/extension_api/models/action_type.py
flix/extension/extension_api/models/actions_in_progress_response.py
flix/extension/extension_api/models/asset_type.py
flix/extension/extension_api/models/bulk_panel_annotate_request.py
flix/extension/extension_api/models/bulk_panel_request.py
flix_sdk-2.0.1.dist-info/METADATA
flix_sdk-2.0.1.dist-info/WHEEL
flix_sdk-2.0.1.dist-info/entry_points.txt
flix_sdk-2.0.1.dist-info/RECORD
