Metadata-Version: 2.1
Name: flix-sdk
Version: 2.0.1
Summary: Python SDK and command-line utilities for Flix
Home-page: https://www.foundry.com/products/flix
License: Apache-2.0
Requires-Python: >=3.10,<4.0
Classifier: License :: OSI Approved :: Apache Software License
Classifier: Programming Language :: Python :: 3
Classifier: Programming Language :: Python :: 3.10
Classifier: Programming Language :: Python :: 3.11
Requires-Dist: aiohttp (>=3.8.5,<4.0.0)
Requires-Dist: anyio (>=3.7.1,<4.0.0)
Requires-Dist: appdirs (>=1.4.4,<2.0.0)
Requires-Dist: asyncclick (>=8.1.3.4,<9.0.0.0)
Requires-Dist: attrs (>=23.1.0,<24.0.0)
Requires-Dist: cryptography (>=41.0.3,<42.0.0)
Requires-Dist: grpcio (>=1.57.0,<2.0.0)
Requires-Dist: httpx (>=0.24.1,<0.25.0)
Requires-Dist: protobuf (>=4.24.1,<5.0.0)
Requires-Dist: python-dateutil (>=2.8.2,<3.0.0)
Requires-Dist: python-socketio (>=5.9.0,<6.0.0)
Requires-Dist: typing-extensions (>=4.9.0,<5.0.0)
Project-URL: Repository, https://github.com/TheFoundryVisionmongers/flix-scripts/tree/master/flixpy
